red_october/__init__.py
red_october/exceptions.py
red_october/red_october.py
red_october/models/__init__.py
red_october/models/enum_user_role.py
red_october/models/enum_user_type.py
red_october/tests/__init__.py
red_october/tests/test_red_october.py
red_october-0.2.1b173.dist-info/top_level.txt
red_october-0.2.1b173.dist-info/METADATA
red_october-0.2.1b173.dist-info/DESCRIPTION.rst
red_october-0.2.1b173.dist-info/metadata.json
red_october-0.2.1b173.dist-info/WHEEL
red_october-0.2.1b173.dist-info/RECORD
