Metadata-Version: 2.0
Name: red-october
Version: 0.2.1b173
Summary: This library will allow you to interact with Red October using Python.
Home-page: https://laslabs.github.io/red-october
Author: LasLabs Inc.
Author-email: support@laslabs.com
License: MIT
Download-URL: https://github.com/LasLabs/red-october
Platform: UNKNOWN
Classifier: Development Status :: 4 - Beta
Classifier: Environment :: Console
Classifier: Intended Audience :: Developers
Classifier: License :: OSI Approved :: MIT License
Classifier: Programming Language :: Python
Classifier: Topic :: Software Development :: Libraries :: Python Modules
Requires-Dist: enum34
Requires-Dist: requests
